mdx_gitlab_links/__init__.py
mdx_gitlab_links/py.typed
mdx_gitlab_links-0.1.0.dist-info/LICENSE
mdx_gitlab_links-0.1.0.dist-info/METADATA
mdx_gitlab_links-0.1.0.dist-info/WHEEL
mdx_gitlab_links-0.1.0.dist-info/top_level.txt
mdx_gitlab_links-0.1.0.dist-info/RECORD
