Metadata-Version: 2.1
Name: mdx-gitlab-links
Version: 0.1.0
Summary: An extension to Python-Markdown which adds support for GitLab-specific references.
Author: Thibaud Gambier
License: BSD 3-Clause License
Project-URL: Homepage, https://pypi.org/project/mdx-gitlab-links
Project-URL: Repository, https://github.com/tahv/gitlab-links
Project-URL: Issue Tracker, https://github.com/tahv/gitlab-links/issues
Project-URL: Changelog, https://github.com/tahv/gitlab-links/blob/main/CHANGELOG.md
Keywords: markdown,python-markdown,gitlab
Classifier: Development Status :: 4 - Beta
Classifier: License :: OSI Approved :: BSD License
Classifier: Operating System :: OS Independent
Classifier: Programming Language :: Python
Classifier: Programming Language :: Python :: 3
Classifier: Programming Language :: Python :: 3.9
Classifier: Programming Language :: Python :: 3.10
Classifier: Programming Language :: Python :: 3.11
Classifier: Programming Language :: Python :: 3.12
Classifier: Programming Language :: Python :: Implementation :: CPython
Classifier: Programming Language :: Python :: Implementation :: PyPy
Classifier: Topic :: Software Development :: Documentation
Classifier: Topic :: Software Development :: Libraries :: Python Modules
Classifier: Topic :: Text Processing :: Markup :: HTML
Classifier: Topic :: Text Processing :: Markup :: Markdown
Requires-Python: >=3.9
License-File: LICENSE
Requires-Dist: markdown >=3.7
